repo_to_text_ai/__init__.py
repo_to_text_ai/cli.py
repo_to_text_ai/core.py
repo_to_text_ai/scanner.py
repo_to_text_ai/utils.py
repo_to_text_ai-0.3.0.dist-info/licenses/LICENSE
repo_to_text_ai-0.3.0.dist-info/METADATA
repo_to_text_ai-0.3.0.dist-info/WHEEL
repo_to_text_ai-0.3.0.dist-info/entry_points.txt
repo_to_text_ai-0.3.0.dist-info/top_level.txt
repo_to_text_ai-0.3.0.dist-info/RECORD
