Metadata-Version: 2.4
Name: repo-to-text-ai
Version: 0.3.0
Summary: A tool to turn an entire Git repository into a single organized text file for AI context.
Author-email: zhu-weijie <byzhubaiyuan@gmail.com>
Project-URL: Homepage, https://github.com/zhu-weijie/repo-to-text-ai
Project-URL: Bug Tracker, https://github.com/zhu-weijie/repo-to-text-ai/issues
Keywords: git,repository,context,ai,llm
Classifier: Programming Language :: Python :: 3
Classifier: License :: OSI Approved :: MIT License
Classifier: Operating System :: OS Independent
Classifier: Development Status :: 4 - Beta
Classifier: Topic :: Software Development
Classifier: Topic :: Utilities
Requires-Python: >=3.8
License-File: LICENSE
Requires-Dist: typer[all]
Requires-Dist: pathspec
Requires-Dist: tqdm
Provides-Extra: test
Requires-Dist: pytest; extra == "test"
Dynamic: license-file
